CHANGELOG.txt
LICENCE.txt
MANIFEST.in
README.md
commands.txt
run.py
setup.py
pipefyUts/__init__.py
pipefyUts/card.py
pipefyUts.egg-info/PKG-INFO
pipefyUts.egg-info/SOURCES.txt
pipefyUts.egg-info/dependency_links.txt
pipefyUts.egg-info/requires.txt
pipefyUts.egg-info/top_level.txt
pipefyUts/graphql/createCard.gql
pipefyUts/graphql/deleteCards.gql
pipefyUts/graphql/getCard.gql
pipefyUts/graphql/listCardsFromPhase.gql
pipefyUts/graphql/listMembers.gql
pipefyUts/graphql/listPhaseFormFields.gql
pipefyUts/graphql/listPipeLabels.gql
pipefyUts/graphql/listStartFormFields.gql
pipefyUts/graphql/presignedUrl.gql
pipefyUts/graphql/updateCardLabels.gql