Metadata-Version: 2.1
Name: pipefyUts
Version: 1.1.6
Summary: Pipefy manipulator
Home-page: 
Author: Melque Lima
Author-email: melque_ex@yahoo.com.br
License: MIT
Keywords: pipefyUts
Classifier: Development Status :: 5 - Production/Stable
Classifier: Intended Audience :: Education
Classifier: Operating System :: Microsoft :: Windows :: Windows 10
Classifier: License :: OSI Approved :: MIT License
Classifier: Programming Language :: Python :: 3
License-File: LICENCE.txt
Requires-Dist: requests
